{
  "project_info": {
    "project_number": "934836649691",
    "project_id": "homework---2",
    "storage_bucket": "homework---2.appspot.com"
  },
  "client": [
    {
      "client_info": {
        "mobilesdk_app_id": "1:934836649691:android:aefa8bc6bcf52b1837d6fe",
        "android_client_info": {
          "package_name": "com.example.modul_5"
        }
      },
      "oauth_client": [],
      "api_key": [
        {
          "current_key": "AIzaSyCm3A6hrWKJ4zX73HE7F4UkS9MHHNrlsk0"
        }
      ],
      "services": {
        "appinvite_service": {
          "other_platform_oauth_client": []
        }
      }
    }
  ],
  "configuration_version": "1"
}